alpaca_farm/__init__.py
alpaca_farm/accelerate_patch.py
alpaca_farm/common.py
alpaca_farm/constants.py
alpaca_farm/data_postprocessor.py
alpaca_farm/data_preprocessor.py
alpaca_farm/data_utils.py
alpaca_farm/distributed_utils.py
alpaca_farm/logging.py
alpaca_farm/openai_utils.py
alpaca_farm/reward_modeling_trainer.py
alpaca_farm/torch_ops.py
alpaca_farm/trainer_utils.py
alpaca_farm/types.py
alpaca_farm/utils.py
alpaca_farm/auto_annotations/__init__.py
alpaca_farm/auto_annotations/eval.py
alpaca_farm/auto_annotations/annotators/annotator_pool_v0/chatml_b1_chat_v0_with_inputs.txt
alpaca_farm/auto_annotations/annotators/annotator_pool_v0/chatml_b1_chat_v0_without_inputs.txt
alpaca_farm/auto_annotations/annotators/annotator_pool_v0/chatml_b1_chat_with_inputs.txt
alpaca_farm/auto_annotations/annotators/annotator_pool_v0/chatml_b1_chat_without_inputs.txt
alpaca_farm/auto_annotations/annotators/annotator_pool_v0/chatml_b1_cot_json_with_inputs.txt
alpaca_farm/auto_annotations/annotators/annotator_pool_v0/chatml_b1_cot_json_without_inputs.txt
alpaca_farm/auto_annotations/annotators/annotator_pool_v0/chatml_b1_with_inputs.txt
alpaca_farm/auto_annotations/annotators/annotator_pool_v0/chatml_b1_without_inputs.txt
alpaca_farm/auto_annotations/annotators/annotator_pool_v0/chatml_b4_cot_json_with_inputs.txt
alpaca_farm/auto_annotations/annotators/annotator_pool_v0/chatml_b4_cot_json_without_inputs.txt
alpaca_farm/auto_annotations/annotators/annotator_pool_v0/chatml_b5_diana_with_inputs.txt
alpaca_farm/auto_annotations/annotators/annotator_pool_v0/chatml_b5_diana_without_inputs.txt
alpaca_farm/auto_annotations/annotators/annotator_pool_v0/chatml_b5_joe_with_inputs.txt
alpaca_farm/auto_annotations/annotators/annotator_pool_v0/chatml_b5_joe_without_inputs.txt
alpaca_farm/auto_annotations/annotators/annotator_pool_v0/chatml_b5_with_inputs.txt
alpaca_farm/auto_annotations/annotators/annotator_pool_v0/chatml_b5_without_inputs.txt
alpaca_farm-0.2.0.dist-info/LICENSE
alpaca_farm-0.2.0.dist-info/METADATA
alpaca_farm-0.2.0.dist-info/WHEEL
alpaca_farm-0.2.0.dist-info/top_level.txt
alpaca_farm-0.2.0.dist-info/RECORD
