Metadata-Version: 2.1
Name: alpaca_farm
Version: 0.2.0
Classifier: Intended Audience :: Developers
Classifier: Intended Audience :: Education
Classifier: Intended Audience :: Science/Research
Classifier: License :: OSI Approved :: Apache Software License
Classifier: Operating System :: OS Independent
Classifier: Programming Language :: Python :: 3.10
Classifier: Programming Language :: Python :: 3.11
Classifier: Programming Language :: Python :: 3.12
Classifier: Topic :: Scientific/Engineering :: Artificial Intelligence
Requires-Python: >=3.10
License-File: LICENSE
Requires-Dist: datasets
Requires-Dist: einops
Requires-Dist: nltk
Requires-Dist: accelerate <=0.20.0,>=0.18.0
Requires-Dist: tabulate
Requires-Dist: transformers <=4.29.2,>=4.26.0
Requires-Dist: statsmodels
Requires-Dist: tiktoken >=0.3.2
Requires-Dist: markdown
Requires-Dist: scikit-learn
Requires-Dist: sentencepiece
Requires-Dist: pandas
Requires-Dist: wandb
Requires-Dist: torch >=1.13.1
Requires-Dist: fire
Requires-Dist: openai
Requires-Dist: alpaca-eval >=0.5.4
Provides-Extra: dev
Requires-Dist: pre-commit >=3.2.0 ; extra == 'dev'
Requires-Dist: black >=23.1.0 ; extra == 'dev'
Requires-Dist: isort ; extra == 'dev'
Provides-Extra: full
Requires-Dist: flash-attn ; extra == 'full'
Requires-Dist: apex ; extra == 'full'
Requires-Dist: deepspeed ; extra == 'full'
Requires-Dist: benepar ; extra == 'full'
Requires-Dist: spacy ; extra == 'full'
Requires-Dist: spacy-fastlang ; extra == 'full'
Requires-Dist: plotly ; extra == 'full'
Requires-Dist: mapply ; extra == 'full'
